.DS_Store
jw_don_confirm/__init__.py
jw_don_confirm/cmd_adapter.py
jw_don_confirm/constants.py
jw_don_confirm/entities.py
jw_don_confirm/json_address_repo.py
jw_don_confirm/json_data_repo.py
jw_don_confirm/json_donations_repo.py
jw_don_confirm/json_masterdata_service.py
jw_don_confirm/py_pdf_adapter.py
jw_don_confirm/read_from26_uc.py
jw_don_confirm/read_from67_uc.py
jw_don_confirm/services.py
jw_don_confirm/write_to67_uc.py
jw_don_confirm-1.2.2.dist-info/METADATA
jw_don_confirm-1.2.2.dist-info/WHEEL
jw_don_confirm-1.2.2.dist-info/entry_points.txt
jw_don_confirm-1.2.2.dist-info/top_level.txt
jw_don_confirm-1.2.2.dist-info/RECORD
