Metadata-Version: 2.1
Name: jw_don_confirm
Version: 1.2.2
Summary: Tool for creating JW Donation Confirmations in Germany
Author-email: Jonathan Frankenberger <jonathan.frankenberger@web.de>
License: GPL-3.0-or-later
Requires-Python: >=3.11
Requires-Dist: num2words ~=0.5.13
Requires-Dist: Babel ~=2.14.0
Requires-Dist: pypdf ~=4.0.2
Requires-Dist: pluggy ~=1.4.0
Requires-Dist: iniconfig ~=2.0.0
Requires-Dist: setuptools ~=69.1.1
Requires-Dist: packaging ~=23.2
Requires-Dist: dataclass-wizard ~=0.22.3
Requires-Dist: dateparser ~=1.2.0
Provides-Extra: tests
Requires-Dist: pytest ; extra == 'tests'
